hmr-0.7.6.2.dist-info/METADATA
hmr-0.7.6.2.dist-info/WHEEL
hmr-0.7.6.2.dist-info/entry_points.txt
reactivity/__init__.py
reactivity/_curried.py
reactivity/_typing_utils.py
reactivity/async_primitives.py
reactivity/collections.py
reactivity/context.py
reactivity/functional.py
reactivity/helpers.py
reactivity/hmr/__init__.py
reactivity/hmr/__main__.py
reactivity/hmr/_common.py
reactivity/hmr/api.py
reactivity/hmr/core.py
reactivity/hmr/exec_hack/__init__.py
reactivity/hmr/exec_hack/transform.py
reactivity/hmr/fs.py
reactivity/hmr/hooks.py
reactivity/hmr/proxy.py
reactivity/hmr/run.py
reactivity/hmr/utils.py
reactivity/primitives.py
hmr-0.7.6.2.dist-info/RECORD
