Metadata-Version: 2.1
Name: hmr
Version: 0.7.6.2
Summary: Hot Module Reload and Fine-grained Reactive Programming for Python
Keywords: reactive-programming,hot-module-reload,signals,hmr
Classifier: Development Status :: 5 - Production/Stable
Classifier: Intended Audience :: Developers
Classifier: Operating System :: OS Independent
Classifier: Topic :: Software Development :: Libraries :: Python Modules
Classifier: Typing :: Typed
Project-URL: Homepage, https://pyth-on-line.promplate.dev/hmr
Project-URL: Documentation, https://hmr.promplate.dev/
Project-URL: Repository, https://github.com/promplate/hmr
Project-URL: Changelog, https://github.com/promplate/pyth-on-line/commits/main/packages/hmr
Requires-Python: >=3.12
Requires-Dist: sniffio~=1.3; sys_platform != "emscripten"
Requires-Dist: watchfiles<2,>=0.21; sys_platform != "emscripten"
